xroute_env/__init__.py
xroute_env-0.0.0.dist-info/LICENSE
xroute_env-0.0.0.dist-info/METADATA
xroute_env-0.0.0.dist-info/WHEEL
xroute_env-0.0.0.dist-info/top_level.txt
xroute_env-0.0.0.dist-info/RECORD
