Metadata-Version: 2.1
Name: xroute-env
Version: 0.0.0
Summary: A standard API for reinforcement learning in detailed routing.
License: BSD-3-Clause
Project-URL: Homepage, https://xplan-lab.org/
Project-URL: Repository, https://github.com/xplanlab/xroute_env
Project-URL: Documentation, https://github.com/xplanlab/xroute_env
Project-URL: Bug Report, https://github.com/xplanlab/xroute_env/issues
Keywords: Reinforcement Learning,VLSI,EDA,RL,AI,detailed routing,gymnasium
Classifier: Development Status :: 2 - Pre-Alpha
Classifier: License :: OSI Approved :: BSD License
Classifier: Programming Language :: Python :: 3
Classifier: Programming Language :: Python :: 3.9
Classifier: Programming Language :: Python :: 3.10
Classifier: Programming Language :: Python :: 3.11
Classifier: Intended Audience :: Science/Research
Classifier: Topic :: Scientific/Engineering :: Artificial Intelligence
Classifier: Topic :: Scientific/Engineering :: Electronic Design Automation (EDA)
Requires-Python: >=3.9
License-File: LICENSE
Requires-Dist: gymnasium (==0.28.1)
